<?xml version="1.0" encoding="utf-8" ?><dwsync><file name="._CHANGELOG.TXT" server="202.46.1.95//var/www/www_simpus/simpus-tanahsareal/" local="3515477448" remote="3515477448" Dst="-1" /><file name="CholeskyDecomposition.php" server="202.46.1.95//var/www/www_simpus/simpus-tanahsareal/" local="3515477448" remote="3515477448" Dst="-1" /><file name="._QRDecomposition.php" server="202.46.1.95//var/www/www_simpus/simpus-tanahsareal/" local="3515477448" remote="3515477448" Dst="-1" /><file name="._SingularValueDecomposition.php" server="202.46.1.95//var/www/www_simpus/simpus-tanahsareal/" local="3515477448" remote="3515477448" Dst="-1" /><file name="._CholeskyDecomposition.php" server="202.46.1.95//var/www/www_simpus/simpus-tanahsareal/" local="3515477448" remote="3515477448" Dst="-1" /><file name="LUDecomposition.php" server="202.46.1.95//var/www/www_simpus/simpus-tanahsareal/" local="3515477448" remote="3515477448" Dst="-1" /><file name="SingularValueDecomposition.php" server="202.46.1.95//var/www/www_simpus/simpus-tanahsareal/" local="3515477448" remote="3515477448" Dst="-1" /><file name="._LUDecomposition.php" server="202.46.1.95//var/www/www_simpus/simpus-tanahsareal/" local="3515477448" remote="3515477448" Dst="-1" /><file name="EigenvalueDecomposition.php" server="202.46.1.95//var/www/www_simpus/simpus-tanahsareal/" local="3515477448" remote="3515477448" Dst="-1" /><file name="QRDecomposition.php" server="202.46.1.95//var/www/www_simpus/simpus-tanahsareal/" local="3515477448" remote="3515477448" Dst="-1" /><file name="Matrix.php" server="202.46.1.95//var/www/www_simpus/simpus-tanahsareal/" local="3515477448" remote="3515477448" Dst="-1" /><file name="CHANGELOG.TXT" server="202.46.1.95//var/www/www_simpus/simpus-tanahsareal/" local="3515477448" remote="3515477448" Dst="-1" /><file name="._EigenvalueDecomposition.php" server="202.46.1.95//var/www/www_simpus/simpus-tanahsareal/" local="3515477448" remote="3515477448" Dst="-1" /><file name="._Matrix.php" server="202.46.1.95//var/www/www_simpus/simpus-tanahsareal/" local="3515477448" remote="3515477448" Dst="-1" /></dwsync>