<?xml version="1.0" encoding="utf-8" ?><dwsync><file name="source_editor.htm" server="202.46.1.95//var/www/www_simpus/simpus-tanahsareal/" local="3515477458" remote="3515477458" Dst="-1" /><file name="shortcuts.htm" server="202.46.1.95//var/www/www_simpus/simpus-tanahsareal/" local="3515477458" remote="3515477458" Dst="-1" /><file name="anchor.htm" server="202.46.1.95//var/www/www_simpus/simpus-tanahsareal/" local="3515477458" remote="3515477458" Dst="-1" /><file name="image.htm" server="202.46.1.95//var/www/www_simpus/simpus-tanahsareal/" local="3515477458" remote="3515477458" Dst="-1" /><file name="editor_template.js" server="202.46.1.95//var/www/www_simpus/simpus-tanahsareal/" local="3515477458" remote="3515477458" Dst="-1" /><file name="about.htm" server="202.46.1.95//var/www/www_simpus/simpus-tanahsareal/" local="3515477458" remote="3515477458" Dst="-1" /><file name="editor_template_src.js" server="202.46.1.95//var/www/www_simpus/simpus-tanahsareal/" local="3515477458" remote="3515477458" Dst="-1" /><file name="charmap.htm" server="202.46.1.95//var/www/www_simpus/simpus-tanahsareal/" local="3515477458" remote="3515477458" Dst="-1" /><file name="link.htm" server="202.46.1.95//var/www/www_simpus/simpus-tanahsareal/" local="3515477458" remote="3515477458" Dst="-1" /><file name="color_picker.htm" server="202.46.1.95//var/www/www_simpus/simpus-tanahsareal/" local="3515477458" remote="3515477458" Dst="-1" /></dwsync>